LICENSE
README.md
pyproject.toml
setup.py
tmodelviz/__init__.py
tmodelviz/simulator.py
tmodelviz/test_simulator.py
tmodelviz/test_utils.py
tmodelviz/test_visualizer.py
tmodelviz/utils.py
tmodelviz/visualizer.py
tmodelviz.egg-info/PKG-INFO
tmodelviz.egg-info/SOURCES.txt
tmodelviz.egg-info/dependency_links.txt
tmodelviz.egg-info/requires.txt
tmodelviz.egg-info/top_level.txt