Metadata-Version: 2.1
Name: tmodelviz
Version: 1.2.0
Summary: A package for Tellurium model visualization.
Home-page: https://github.com/yourusername/tmodelviz
Author: Shajesh Sharma
Author-email: shajesh.sharma@colorado.edu
License: UNKNOWN
Platform: UNKNOWN
Classifier: Programming Language :: Python :: 3
Classifier: License :: OSI Approved :: MIT License
Classifier: Operating System :: OS Independent
Requires-Python: >=3.8
License-File: LICENSE
